streamlined/__init__.py
streamlined/common/__init__.py
streamlined/common/argument_parsing.py
streamlined/common/callables.py
streamlined/common/constants.py
streamlined/common/data_structures.py
streamlined/common/dictionary.py
streamlined/common/functionmaker.py
streamlined/common/logging.py
streamlined/common/names.py
streamlined/common/predicates.py
streamlined/common/subprocess.py
streamlined/common/template.py
streamlined/common/transforms.py
streamlined/common/tree.py
streamlined/execution/__init__.py
streamlined/execution/executor.py
streamlined/middlewares/__init__.py
streamlined/middlewares/action.py
streamlined/middlewares/argument.py
streamlined/middlewares/bound_middleware.py
streamlined/middlewares/cleanup.py
streamlined/middlewares/context.py
streamlined/middlewares/log.py
streamlined/middlewares/middleware.py
streamlined/middlewares/middlewares.py
streamlined/middlewares/name.py
streamlined/middlewares/parser.py
streamlined/middlewares/pipeline.py
streamlined/middlewares/runstage.py
streamlined/middlewares/runstep.py
streamlined/middlewares/setup.py
streamlined/middlewares/skip.py
streamlined/middlewares/suppress.py
streamlined/middlewares/validator.py
streamlined/parsing/__init__.py
streamlined/parsing/parser.py
streamlined/parsing/simplification.py
streamlined/parsing/variant.py
streamlined/scheduling/__init__.py
streamlined/scheduling/requirements.py
streamlined/scheduling/schedule.py
streamlined/scheduling/scheduler.py
streamlined/scheduling/unit.py
streamlined/services/__init__.py
streamlined/services/dependency_injection.py
streamlined/services/dependency_tracking.py
streamlined/services/event_notification.py
streamlined/services/reference.py
streamlined/services/scoping.py
streamlined/services/storage.py
streamlined/settings/__init__.py
streamlined/settings/settings.py
streamlined/utils/__init__.py
streamlined/utils/asyncfile.py
streamlined/utils/common.py
streamlined/utils/dictcmp.py
streamlined/utils/path.py
streamlined-0.4.5.dist-info/LICENSE
streamlined-0.4.5.dist-info/METADATA
streamlined-0.4.5.dist-info/WHEEL
streamlined-0.4.5.dist-info/top_level.txt
streamlined-0.4.5.dist-info/RECORD
