Metadata-Version: 2.1
Name: streamlined
Version: 0.4.5
Summary: Make ML or generic pipeline more streamlined
Home-page: https://github.com/pengzhengyi/Streamlined
Author: Zhengyi Peng
Author-email: pengzhengyipengzhengyi@gmail.com
License: UNKNOWN
Project-URL: Bug Tracker, https://github.com/pengzhengyi/Streamlined/issues
Project-URL: Documentation, https://github.com/pengzhengyi/Streamlined/wiki
Keywords: workflow pipeline
Platform: UNKNOWN
Classifier: Programming Language :: Python :: 3
Classifier: License :: OSI Approved :: MIT License
Classifier: Operating System :: OS Independent
Requires-Python: >=3.9
License-File: LICENSE
Requires-Dist: ray[default]
Requires-Dist: treelib
Requires-Dist: diskcache
Requires-Dist: networkx[default]
Requires-Dist: decorator
Requires-Dist: wrapt
Requires-Dist: matplotlib
Requires-Dist: pydot
Requires-Dist: aiorun
Requires-Dist: uvloop
Requires-Dist: aiofile
Requires-Dist: pqdict
Requires-Dist: aiofiles
Requires-Dist: nest-asyncio
Requires-Dist: rich
